pydra/tasks/fsl/__init__.py
pydra/tasks/fsl/_version.py
pydra/tasks/fsl/latest.py
pydra/tasks/fsl/v6/__init__.py
pydra/tasks/fsl/v6/_post_release.py
pydra/tasks/fsl/v6/base.py
pydra/tasks/fsl/v6/aroma/__init__.py
pydra/tasks/fsl/v6/aroma/ica__aroma.py
pydra/tasks/fsl/v6/dti/__init__.py
pydra/tasks/fsl/v6/dti/bedpostx5.py
pydra/tasks/fsl/v6/dti/distance_map.py
pydra/tasks/fsl/v6/dti/dti_fit.py
pydra/tasks/fsl/v6/dti/find_the_biggest.py
pydra/tasks/fsl/v6/dti/make_dyadic_vectors.py
pydra/tasks/fsl/v6/dti/prob_track_x.py
pydra/tasks/fsl/v6/dti/prob_track_x2.py
pydra/tasks/fsl/v6/dti/proj_thresh.py
pydra/tasks/fsl/v6/dti/tract_skeleton.py
pydra/tasks/fsl/v6/dti/vec_reg.py
pydra/tasks/fsl/v6/dti/x_fibres_5.py
pydra/tasks/fsl/v6/epi/__init__.py
pydra/tasks/fsl/v6/epi/apply_topup.py
pydra/tasks/fsl/v6/epi/eddy.py
pydra/tasks/fsl/v6/epi/eddy_correct.py
pydra/tasks/fsl/v6/epi/eddy_quad.py
pydra/tasks/fsl/v6/epi/epi_de_warp.py
pydra/tasks/fsl/v6/epi/epi_reg.py
pydra/tasks/fsl/v6/epi/prepare_fieldmap.py
pydra/tasks/fsl/v6/epi/topup.py
pydra/tasks/fsl/v6/fix/__init__.py
pydra/tasks/fsl/v6/fix/accuracy_tester.py
pydra/tasks/fsl/v6/fix/classifier.py
pydra/tasks/fsl/v6/fix/cleaner.py
pydra/tasks/fsl/v6/fix/feature_extractor.py
pydra/tasks/fsl/v6/fix/training.py
pydra/tasks/fsl/v6/fix/training_set_creator.py
pydra/tasks/fsl/v6/maths/__init__.py
pydra/tasks/fsl/v6/maths/apply_mask.py
pydra/tasks/fsl/v6/maths/ar1_image.py
pydra/tasks/fsl/v6/maths/binary_maths.py
pydra/tasks/fsl/v6/maths/change_data_type.py
pydra/tasks/fsl/v6/maths/dilate_image.py
pydra/tasks/fsl/v6/maths/erode_image.py
pydra/tasks/fsl/v6/maths/isotropic_smooth.py
pydra/tasks/fsl/v6/maths/maths_command.py
pydra/tasks/fsl/v6/maths/max_image.py
pydra/tasks/fsl/v6/maths/maxn_image.py
pydra/tasks/fsl/v6/maths/mean_image.py
pydra/tasks/fsl/v6/maths/median_image.py
pydra/tasks/fsl/v6/maths/min_image.py
pydra/tasks/fsl/v6/maths/multi_image_maths.py
pydra/tasks/fsl/v6/maths/percentile_image.py
pydra_tasks_fsl-0.3.1.dist-info/METADATA
pydra_tasks_fsl-0.3.1.dist-info/WHEEL
pydra_tasks_fsl-0.3.1.dist-info/licenses/LICENSE
pydra_tasks_fsl-0.3.1.dist-info/licenses/NOTICE
pydra_tasks_fsl-0.3.1.dist-info/RECORD
